Metadata-Version: 2.1
Name: django-smart-lists
Version: 1.4.1
Summary: Easy lists for django views
Home-page: https://github.com/plecto/django-smart-lists
Author: Kristian Oellegaard
Author-email: kristian@kristian.io
License: MIT License
Platform: UNKNOWN
Classifier: Environment :: Web Environment
Classifier: Framework :: Django
Classifier: Intended Audience :: Developers
Classifier: License :: OSI Approved :: MIT License
Classifier: Operating System :: OS Independent
Classifier: Programming Language :: Python
Classifier: Programming Language :: Python :: 3
Classifier: Programming Language :: Python :: 3.4
Classifier: Programming Language :: Python :: 3.5
Classifier: Topic :: Internet :: WWW/HTTP
Classifier: Topic :: Internet :: WWW/HTTP :: Dynamic Content
Requires-Dist: openpyxl (<3.1)
